<?xml version="1.0" encoding="utf-8"?>
<GameData>
	<Language_en_US>
		<Row Tag="TXT_KEY_TECH_MYTHOLOGY_TITLE">
			<Text>Mythology</Text>
		</Row>
		<Row Tag="TXT_KEY_TECH_MECHANISTIC_WORLDVIEW_TITLE">
			<Text>Mechanistic World View</Text>
		</Row>
		<Row Tag="TXT_KEY_TECH_ORGANIC_WORLDVIEW_TITLE">
			<Text>Organic World View</Text>
		</Row>
		<Row Tag="TXT_KEY_TECH_LOGICAL_REASONING_TITLE">
			<Text>Logical Reasoning</Text>
		</Row>
		<Row Tag="TXT_KEY_TECH_ASSOCIATIVE_THINKING_TITLE">
			<Text>Associative Thinking</Text>
		</Row>
		<Row Tag="TXT_KEY_TECH_QUANTIFICATION_TITLE">
			<Text>Quantification</Text>
		</Row>
		<Row Tag="TXT_KEY_TECH_HERBAL_MEDICINE_TITLE">
			<Text>Herbal Medicine</Text>
		</Row>
		<Row Tag="TXT_KEY_TECH_GRAPHICAL_ANALYSIS_TITLE">
			<Text>Graphical Analysis</Text>
		</Row>
		<Row Tag="TXT_KEY_TECH_QIGONG_TITLE">
			<Text>Qi Gong</Text>
		</Row>
		<Row Tag="TXT_KEY_TECH_EXPERIMENTATION_TITLE">
			<Text>Experimentation</Text>
		</Row>
	</Language_en_US>
</GameData>